{
  "message":"",
  "statuscode":100,
   "post":[
      {
        "id":"1",
        "name":"Abia",
        "lat":"5.532003041",
        "log":"7.486002487"
    },
    {
      "id":"2",
      "name":"Adamawa",
      "lat":"10.2703408",
      "log":"13.2700321"
   },
   {
    "id":"3",
    "name":"Akwa Ibom",
    "lat":"5.007996056",
    "log":"7.849998524"
  },
  {
  "id":"4",
  "name":"Anambra",
  "lat":"6.210433572",
  "log":"7.06999711"
  },
  {
    "id":"5",
    "name":"Bauchi",
    "lat":"11.68040977",
    "log":"10.19001339"
  },
  {
    "id":"32",
    "name":"Bayelsa",
    "lat":"5.2238996",
    "log":"6.40868560"
    },
   
  {
  "id":"6",
  "name":"Benue",
  "lat":"7.190399596",
  "log":"8.129984089"
  },
  {
  "id":"7",
  "name":"Borno",
  "lat":"10.62042279",
  "log":"12.18999467"
  },
  {
  "id":"8",
  "name":"Cross River",
  "lat":"4.960406513",
  "log":"8.330023558"
  },
  {
    "id":"9",
    "name":"Delta",
    "lat":"5.890427265",
    "log":"5.680004434"
  },
  {
    "id":"33",
    "name":"Ebonyi",
    "lat":"6.3252763",
    "log":"8.0943573"
    },
  {
  "id":"10",
  "name":"Edo",
  "lat":"6.340477314",
  "log":"5.620008096"
  },
  {
  "id":"11",
  "name":"Ekiti",
  "lat":"7.630372741",
  "log":"5.219980834"
  },
  {
  "id":"12",
  "name":"Enugu",
  "lat":"6.867034321",
  "log":"7.383362995"
  },
  {
  "id":"13",
  "name":"Gombe",
  "lat":"10.29044293",
  "log":"11.16995357"
  },
  {
  "id":"14",
  "name":"Imo",
  "lat":"5.492997053",
  "log":"7.026003588"
  },
  {
  "id":"15",
  "name":"Jigawa",
  "lat":"11.7991891",
  "log":"9.350334607"
  },
  {
  "id":"16",
  "name":"Kaduna",
  "lat":"11.0799813",
  "log":"7.710009724"
  },
  {
    "id":"17",
    "name":"Kano",
    "lat":"11.99997683",
    "log":"8.5200378"
    },
    {
    "id":"18",
    "name":"Katsina",
    "lat":"11.5203937",
    "log":"7.320007689"
    },
    {
    "id":"19",
    "name":"Kebbi",
    "lat":"12.45041445",
    "log":"4.199939737"
    },
    {
    "id":"20",
    "name":"Kogi",
    "lat":"7.800388203",
    "log":"6.739939737"
    },
    {
    "id":"21",
    "name":"Kwara",
    "lat":"8.490010192",
    "log":"4.549995889"
    },
    {
    "id":"22",
    "name":"Lagos",
    "lat":"6.443261653",
    "log":"3.391531071"
    },
    {
      "id":"23",
      "name":"Nassarawa",
      "lat":"8.490423603",
      "log":"8.5200378"
      },
      {
      "id":"24",
      "name":"Niger",
      "lat":"10.4003587",
      "log":"5.469939737"
      },
      {
      "id":"25",
      "name":"Ogun",
      "lat":"7.160427265",
      "log":"3.350017455"
      },
      {
        "id":"26",
        "name":"Ondo",
        "lat":"7.250395934",
        "log":"5.199982054"
        },
        {
          "id":"27",
          "name":"Osun",
          "lat":"7.629959329",
          "log":"4.179992634"
          },
          {
          "id":"28",
          "name":"Oyo",
          "lat":"7.970016092",
          "log":"3.590002806"
          },
          {
          "id":"29",
          "name":"Plateau",
          "lat":"9.929973978",
          "log":"8.890041055"
          },
          {
            "id":"30",
            "name":"Rivers",
            "lat":"4.810002257",
            "log":"7.010000772"
            },
            {
              "id":"31",
              "name":"Sokoto",
              "lat":"13.06001548",
              "log":"5.240031289"
              },       
                {
                  "id":"34",
                  "name":"Taraba",
                  "lat":"7.870409769",
                  "log":"9.780012572"
                  },
                  {
                  "id":"35",
                  "name":"Yobe",
                  "lat":"11.74899608",
                  "log":"11.96600457"
                  },
                  {
                  "id":"36",
                  "name":"Zamfara",
                  "lat":"12.1704057",
                  "log":"6.659996296"
                  },
                  {
                    "id":"37",
                    "name":"Federal Capital Territory",
                    "lat":"9.083333149",
                    "log":"7.533328002"
                    }
     
  ]
  }